{
  "frames": {
    "shoot0000": {
      "frame": {
        "x": 33,
        "y": 8,
        "w": 64,
        "h": 32
      }
    },
    "shoot0001": {
      "frame": {
        "x": 97,
        "y": 8,
        "w": 64,
        "h": 32
      }
    },
    "shoot0002": {
      "frame": {
        "x": 161,
        "y": 8,
        "w": 64,
        "h": 32
      }
    },
    "shoot0003": {
      "frame": {
        "x": 225,
        "y": 8,
        "w": 64,
        "h": 32
      }
    },
    "shoot0004": {
      "frame": {
        "x": 289,
        "y": 8,
        "w": 64,
        "h": 32
      }
    },
    "shoot0005": {
      "frame": {
        "x": 353,
        "y": 8,
        "w": 64,
        "h": 32
      }
    },
    "shoot0006": {
      "frame": {
        "x": 609,
        "y": 8,
        "w": 64,
        "h": 32
      }
    },
    "shoot0007": {
      "frame": {
        "x": 673,
        "y": 8,
        "w": 64,
        "h": 32
      }
    },
    "shoot0008": {
      "frame": {
        "x": 922,
        "y": 3,
        "w": 64,
        "h": 32
      }
    },
    "shoot0009": {
      "frame": {
        "x": 988,
        "y": 1,
        "w": 64,
        "h": 32
      }
    },
    "shoot0010": {
      "frame": {
        "x": 1057,
        "y": 8,
        "w": 64,
        "h": 32
      }
    },
    "shoot0011": {
      "frame": {
        "x": 1152,
        "y": 5,
        "w": 64,
        "h": 32
      }
    },
    "shoot0012": {
      "frame": {
        "x": 1377,
        "y": 8,
        "w": 64,
        "h": 32
      }
    },
    "shoot0013": {
      "frame": {
        "x": 1569,
        "y": 8,
        "w": 64,
        "h": 32
      }
    },
    "shoot0014": {
      "frame": {
        "x": 417,
        "y": 9,
        "w": 64,
        "h": 32
      }
    },
    "shoot0015": {
      "frame": {
        "x": 480,
        "y": 10,
        "w": 64,
        "h": 32
      }
    },
    "shoot0016": {
      "frame": {
        "x": 1280,
        "y": 3,
        "w": 64,
        "h": 32
      }
    },
    "shoot0017": {
      "frame": {
        "x": 1408,
        "y": 2,
        "w": 64,
        "h": 32
      }
    },
    "shoot0018": {
      "frame": {
        "x": 1472,
        "y": 1,
        "w": 64,
        "h": 32
      }
    },
    "shoot0019": {
      "frame": {
        "x": 1112,
        "y": 2,
        "w": 64,
        "h": 32
      }
    },
    "shoot0020": {
      "frame": {
        "x": 546,
        "y": 6,
        "w": 64,
        "h": 32
      }
    },
    "shoot0021": {
      "frame": {
        "x": 798,
        "y": 6,
        "w": 64,
        "h": 32
      }
    },
    "shoot0022": {
      "frame": {
        "x": 861,
        "y": 6,
        "w": 64,
        "h": 32
      }
    },
    "shoot0023": {
      "frame": {
        "x": 737,
        "y": 7,
        "w": 64,
        "h": 32
      }
    },
    "shoot0024": {
      "frame": {
        "x": 1216,
        "y": 6,
        "w": 64,
        "h": 32
      }
    }
  }
}
